rtl/fpadd.v
module fpadd
#(
    parameter DWIDTH = 32,
    parameter EWIDTH = 8,
    parameter MWIDTH = 23
)
(
    input clk,
    input rst,
    input valid,
    input [DWIDTH-1:0] a,
    input [DWIDTH-1:0] b,
    output reg [DWIDTH-1:0] sum,
    output reg [2:0] fex,
    output reg done
);
    // Valid signal pipeline tracking
    reg valid_s1, valid_s2, valid_s3, valid_s4;
    
    always @(posedge clk or posedge rst) begin
        if (rst) begin
            valid_s1 <= 0;
            valid_s2 <= 0;
            valid_s3 <= 0;
            valid_s4 <= 0;
        end else begin
            valid_s1 <= valid;
            valid_s2 <= valid_s1;
            valid_s3 <= valid_s2;
            valid_s4 <= valid_s3;
        end
    end

    // Stage 0 registers
    reg [EWIDTH-1:0] expa_s0, expb_s0;
    reg [MWIDTH-1:0] mana_s0, manb_s0;
    reg sign_a, sign_b;

    always @(posedge clk or posedge rst) begin
        if(rst) begin
            expa_s0 <= 0;
            expb_s0 <= 0;
            mana_s0 <= 0;
            manb_s0 <= 0;
            sign_a <= 0;
            sign_b <= 0;
        end else begin
            if (valid) begin
                expa_s0 <= a[DWIDTH-2 : DWIDTH-1-EWIDTH];
                expb_s0 <= b[DWIDTH-2 : DWIDTH-1-EWIDTH];
                mana_s0 <= a[MWIDTH-1:0];
                manb_s0 <= b[MWIDTH-1:0];
                sign_a <= a[DWIDTH-1];
                sign_b <= b[DWIDTH-1];
            end
        end
    end

    wire [EWIDTH-1:0] expa_wire_s0, expb_wire_s0;
    wire [MWIDTH-1:0] mana_wire_s0, manb_wire_s0;
    wire sign_a_wire_s0, sign_b_wire_s0;

    assign expa_wire_s0 = expa_s0;
    assign expb_wire_s0 = expb_s0;
    assign mana_wire_s0 = mana_s0;
    assign manb_wire_s0 = manb_s0;
    assign sign_a_wire_s0 = sign_a;
    assign sign_b_wire_s0 = sign_b;

    // Special case detection
    wire isnan_a, isnan_b;
    wire isinf_a, isinf_b;
    wire issubnorm_a, issubnorm_b;
    wire iszero_a, iszero_b;

    assign isnan_b     = ((expb_wire_s0 == {(EWIDTH){1'b1}})  &&  (manb_wire_s0 != 0));
    assign isnan_a     = ((expa_wire_s0 == {(EWIDTH){1'b1}})  &&  (mana_wire_s0 != 0));
    assign isinf_a     = ((expa_wire_s0 == {(EWIDTH){1'b1}})  &&  (mana_wire_s0 == 0));
    assign isinf_b     = ((expb_wire_s0 == {(EWIDTH){1'b1}})  &&  (manb_wire_s0 == 0));
    assign issubnorm_a = ((expa_wire_s0 == 0)                 &&  (mana_wire_s0 != 0));
    assign issubnorm_b = ((expb_wire_s0 == 0)                 &&  (manb_wire_s0 != 0));
    assign iszero_a    = ((expa_wire_s0 == 0)                 &&  (mana_wire_s0 == 0));
    assign iszero_b    = ((expb_wire_s0 == 0)                 &&  (manb_wire_s0 == 0));

    // Stage 0 special case handling
    reg [MWIDTH + 2:0] mana_full, manb_full;
    reg special_case_s0;
    reg [DWIDTH-1:0] special_result_s0;
    reg [2:0] special_fex_s0;
    reg [DWIDTH-1:0] input_a_s0, input_b_s0; // Store original inputs for special cases

    always @(posedge clk or posedge rst) begin
        if(rst) begin
            special_case_s0 <= 0;
            special_result_s0 <= 0;
            special_fex_s0 <= 0;
            input_a_s0 <= 0;
            input_b_s0 <= 0;
        end else begin
            if (valid) begin
                input_a_s0 <= a;
                input_b_s0 <= b;
            end
            
            mana_full <= {~issubnorm_a, mana_wire_s0, 2'b0};
            manb_full <= {~issubnorm_b, manb_wire_s0, 2'b0};

            // Handle special cases
            if (isnan_a || isnan_b) begin
                special_case_s0 <= 1;
                special_result_s0 <= {1'b0, {EWIDTH{1'b1}}, 1'b1, {MWIDTH-1{1'b0}}}; 
                special_fex_s0 <= 3'b001;  
            end
            else if (isinf_a && isinf_b && (sign_a_wire_s0 != sign_b_wire_s0)) begin
                special_case_s0 <= 1;
                special_result_s0 <= {1'b0, {EWIDTH{1'b1}}, 1'b1, {MWIDTH-1{1'b0}}}; 
                special_fex_s0 <= 3'b001; 
            end
            else if (isinf_a) begin
                special_case_s0 <= 1;
                special_result_s0 <= {sign_a_wire_s0, {EWIDTH{1'b1}}, {MWIDTH{1'b0}}};
                special_fex_s0 <= 3'b000;
            end
            else if (isinf_b) begin
                special_case_s0 <= 1;
                special_result_s0 <= {sign_b_wire_s0, {EWIDTH{1'b1}}, {MWIDTH{1'b0}}};
                special_fex_s0 <= 3'b000;
            end
            else if (iszero_a && iszero_b) begin
                special_case_s0 <= 1;
                special_result_s0 <= {(sign_a_wire_s0 & sign_b_wire_s0), {EWIDTH{1'b0}}, {MWIDTH{1'b0}}};
                special_fex_s0 <= 3'b000;
            end
            else if (iszero_a) begin
                special_case_s0 <= 1;
                special_result_s0 <= input_b_s0;
                special_fex_s0 <= 3'b000;
            end
            else if (iszero_b) begin
                special_case_s0 <= 1;
                special_result_s0 <= input_a_s0;
                special_fex_s0 <= 3'b000;
            end
            else begin
                special_case_s0 <= 0;
                special_result_s0 <= 0;
                special_fex_s0 <= 0;
            end
        end
    end

    // Stage 1: Mantissa alignment based on exponent difference
    reg signed [EWIDTH:0] expdiff_s1;
    reg [MWIDTH + 4 : 0] mana_imm_s1, manb_imm_s1;
    reg [EWIDTH-1:0] max_exp_s1;
    reg sign_a_s1, sign_b_s1;
    reg special_case_s1;
    reg [DWIDTH-1:0] special_result_s1;
    reg [2:0] special_fex_s1;

    always @(posedge clk or posedge rst) begin
        if (rst) begin
            expdiff_s1 <= 0;
            mana_imm_s1 <= 0;
            manb_imm_s1 <= 0;
            max_exp_s1 <= 0;
            sign_a_s1 <= 0;
            sign_b_s1 <= 0;
            special_case_s1 <= 0;
            special_result_s1 <= 0;
            special_fex_s1 <= 0;
        end else begin
            expdiff_s1 <= expa_wire_s0 - expb_wire_s0;
            sign_a_s1 <= sign_a_wire_s0;
            sign_b_s1 <= sign_b_wire_s0;
            special_case_s1 <= special_case_s0;
            special_result_s1 <= special_result_s0;
            special_fex_s1 <= special_fex_s0;

            if (expdiff_s1 < 0) begin
                mana_imm_s1 <= ({1'b0, mana_full, 2'b0} >> (-expdiff_s1));
                manb_imm_s1 <= {1'b0, manb_full, 2'b0};
                max_exp_s1 <= expb_wire_s0;
            end
            else begin
                manb_imm_s1 <= ({1'b0, manb_full, 2'b0} >> expdiff_s1);
                mana_imm_s1 <= {1'b0, mana_full, 2'b0};
                max_exp_s1 <= expa_wire_s0;
            end
        end
    end

    // Stage 2: Addition/Subtraction
    reg [MWIDTH + 5:0] man_result_s2;
    reg [EWIDTH-1:0] exp_result_s2;
    reg sign_result_s2;
    reg special_case_s2;
    reg [DWIDTH-1:0] special_result_s2;
    reg [2:0] special_fex_s2;
    always @(posedge clk or posedge rst) begin
        if (rst) begin
            man_result_s2 <= 0;
            exp_result_s2 <= 0;
            sign_result_s2 <= 0;
            special_case_s2 <= 0;
            special_result_s2 <= 0;
            special_fex_s2 <= 0;
        end else begin
            special_case_s2 <= special_case_s1;
            special_result_s2 <= special_result_s1;
            special_fex_s2 <= special_fex_s1;
            exp_result_s2 <= max_exp_s1;

            if (sign_a_s1 == sign_b_s1) begin
                man_result_s2 <= mana_imm_s1 + manb_imm_s1;
                sign_result_s2 <= sign_a_s1;
            end else begin
                if (mana_imm_s1 >= manb_imm_s1) begin
                    man_result_s2 <= mana_imm_s1 - manb_imm_s1;
                    sign_result_s2 <= sign_a_s1;
                end else begin
                    man_result_s2 <= manb_imm_s1 - mana_imm_s1;
                    sign_result_s2 <= sign_b_s1;
                end
            end
        end
    end

    // Stage 3: Normalization
    reg [MWIDTH + 5:0] man_normalized_s3;
    reg [EWIDTH-1:0] exp_normalized_s3;
    reg sign_result_s3;
    reg special_case_s3;
    reg [DWIDTH-1:0] special_result_s3;
    reg [2:0] special_fex_s3;
    
    function [5:0] count_leading_zeros;
        input [MWIDTH+5:0] mantissa;
        integer j;
        reg found;
        begin
            count_leading_zeros = 0;
            found = 0;
            for (j = MWIDTH + 5; j >= 0; j = j - 1) begin
                if (mantissa[j] && !found) begin
                    count_leading_zeros = (MWIDTH + 5) - j;
                    found = 1;
                end else if ((j == 0) && !found) begin
                    count_leading_zeros = MWIDTH + 6;
                end
            end
            count_leading_zeros = count_leading_zeros - 1;
        end
    endfunction

    always @(posedge clk or posedge rst) begin
        if (rst) begin
            man_normalized_s3 <= 0;
            exp_normalized_s3 <= 0;
            sign_result_s3 <= 0;
            special_case_s3 <= 0;
            special_result_s3 <= 0;
            special_fex_s3 <= 0;
        end else begin
            special_case_s3 <= special_case_s2;
            special_result_s3 <= special_result_s2;
            special_fex_s3 <= special_fex_s2;
            sign_result_s3 <= sign_result_s2;

            if (man_result_s2 == 0) begin
                // Result is zero
                man_normalized_s3 <= 0;
                exp_normalized_s3 <= 0;
            end else if (man_result_s2[MWIDTH + 5]) begin
                // Overflow, shift right
                man_normalized_s3 <= man_result_s2 >> 1;
                exp_normalized_s3 <= exp_result_s2 + 1;
            end else if (!man_result_s2[MWIDTH + 4]) begin
                // Underflow, shift left
                man_normalized_s3 <= man_result_s2 << count_leading_zeros(man_result_s2);
                exp_normalized_s3 <= exp_result_s2 - count_leading_zeros(man_result_s2);
            end else begin
                // Normal case
                man_normalized_s3 <= man_result_s2;
                exp_normalized_s3 <= exp_result_s2;
            end
        end
    end
    reg round_bit, sticky_bit, guard_bit, round_up;
    reg [MWIDTH-1:0] final_mantissa;

    // Stage 4: Rounding and final result
    always @(posedge clk or posedge rst) begin
        if (rst) begin
            sum <= 0;
            fex <= 0;
            done <= 0;
        end else begin
            // Done signal indicates when result is valid
            done <= valid_s4;
            
            if (valid_s4) begin
                if (special_case_s3) begin
                    sum <= special_result_s3;
                    fex <= special_fex_s3;
                end else begin
                    // check for exceptions
                    if (exp_normalized_s3 >= {EWIDTH{1'b1}}) begin
                        // overflow
                        sum <= {sign_result_s3, {EWIDTH{1'b1}}, {MWIDTH{1'b0}}};
                        fex <= 3'b100; 
                    end else if (exp_normalized_s3 == 0) begin
                        // Underflow
                        sum <= {sign_result_s3, {EWIDTH{1'b0}}, {MWIDTH{1'b0}}};
                        fex <= 3'b010;
                    end else begin
                        // Normal result with rounding
                        round_bit = man_normalized_s3[2];
                        sticky_bit = |man_normalized_s3[1:0];
                        guard_bit = man_normalized_s3[3];
                        round_up = round_bit & (guard_bit | sticky_bit);
                        
                        final_mantissa = man_normalized_s3[MWIDTH+3:4] + round_up;
                        sum <= {sign_result_s3, exp_normalized_s3, final_mantissa};
                        fex <= (round_up) ? 3'b001 : 3'b000;
                    end
                end
            end
        end
    end

endmodule

tb/fpadd_tb.v
`timescale 1ns/1ps

module fpadd_tb;

    // Parameters for single and double
    parameter DWIDTH_S = 32;
    parameter EWIDTH_S = 8;
    parameter MWIDTH_S = 23;

    parameter DWIDTH_D = 64;
    parameter EWIDTH_D = 11;
    parameter MWIDTH_D = 52;

    reg clk, rst, valid;
    reg [DWIDTH_S-1:0] a_s, b_s;
    reg [DWIDTH_D-1:0] a_d, b_d;
    wire [DWIDTH_S-1:0] sum_s;
    wire [DWIDTH_D-1:0] sum_d;
    wire [2:0] fex_s, fex_d;
    wire done_s, done_d;

    // Instantiate DUT (single precision)
    fpadd #(
        .DWIDTH(DWIDTH_S),
        .EWIDTH(EWIDTH_S),
        .MWIDTH(MWIDTH_S)
    ) dut_single (
        .clk(clk), .rst(rst), .valid(valid),
        .a(a_s), .b(b_s),
        .sum(sum_s), .fex(fex_s), .done(done_s)
    );

    // Instantiate DUT (double precision)
    fpadd #(
        .DWIDTH(DWIDTH_D),
        .EWIDTH(EWIDTH_D),
        .MWIDTH(MWIDTH_D)
    ) dut_double (
        .clk(clk), .rst(rst), .valid(valid),
        .a(a_d), .b(b_d),
        .sum(sum_d), .fex(fex_d), .done(done_d)
    );

    // Clock generation
    initial begin
        clk = 0;
        forever #5 clk = ~clk;   // 100 MHz
    end

    // Helper task for printing results
    task print_result;
        input [1023:0] name;
        begin
            $display("| %-25s | Single: sum=0x%h fex=%b | Double: sum=0x%h fex=%b |",
                     name, sum_s, fex_s, sum_d, fex_d);
        end
    endtask

    // Stimulus
    initial begin
        $display("==== Floating Point Adder Testbench (Regular Numbers Only) ====");
        $dumpfile("fpadd_tb.vcd");
        $dumpvars(0, fpadd_tb);

        rst = 1;
        valid = 0;
        a_s = 0; b_s = 0;
        a_d = 0; b_d = 0;

        #20 rst = 0;

        // Regular number tests only
        // Test 1
        valid = 1;
        a_s = 32'h41200000; a_d = 64'h4034000000000000; // 10.0
        b_s = 32'h41600000; b_d = 64'h4039000000000000; // 14.0
        #20 valid = 0; #50 print_result("10.0 + 14.0");

        // Test 2
        valid = 1;
        a_s = 32'h42200000; a_d = 64'h4044000000000000; // 40.0
        b_s = 32'h42A00000; b_d = 64'h404E000000000000; // 80.0
        #20 valid = 0; #50 print_result("40.0 + 80.0");

        // Test 3
        valid = 1;
        a_s = 32'h3F800000; a_d = 64'h3FF0000000000000; // 1.0
        b_s = 32'h40000000; b_d = 64'h4000000000000000; // 2.0
        #20 valid = 0; #50 print_result("1.0 + 2.0");

        // Test 4
        valid = 1;
        a_s = 32'h42700000; a_d = 64'h4055000000000000; // 60.0
        b_s = 32'h42F00000; b_d = 64'h4062000000000000; // 120.0
        #20 valid = 0; #50 print_result("60.0 + 120.0");

        // Test 5
        valid = 1;
        a_s = 32'h447A0000; a_d = 64'h40E4000000000000; // 1000.0
        b_s = 32'h44FA0000; b_d = 64'h4113880000000000; // 2000.5
        #20 valid = 0; #50 print_result("1000.0 + 2000.5");

        // Test 6
        valid = 1;
        a_s = 32'h461C4000; a_d = 64'h412E848000000000; // 10000.0
        b_s = 32'h469C4000; b_d = 64'h4173880000000000; // 20000.0
        #20 valid = 0; #50 print_result("10000.0 + 20000.0");

        // Test 7
        valid = 1;
        a_s = 32'h3FA66666; a_d = 64'h3FF199999999999A; // 1.3
        b_s = 32'h40266666; b_d = 64'h4004CCCCCCCCCCCD; // 2.6
        #20 valid = 0; #50 print_result("1.3 + 2.6");

        // Test 8
        valid = 1;
        a_s = 32'h40A00000; a_d = 64'h4014000000000000; // 5.0
        b_s = 32'hC0A00000; b_d = 64'hC014000000000000; // -5.0
        #20 valid = 0; #50 print_result("5.0 + -5.0");

        // Test 9
        valid = 1;
        a_s = 32'hC1200000; a_d = 64'hC034000000000000; // -10.0
        b_s = 32'h41600000; b_d = 64'h4039000000000000; // 14.0
        #20 valid = 0; #50 print_result("-10.0 + 14.0");

        // Test 10
        valid = 1;
        a_s = 32'hC2480000; a_d = 64'hC045000000000000; // -50.0
        b_s = 32'h41A00000; b_d = 64'h403A000000000000; // 20.0
        #20 valid = 0; #50 print_result("-50.0 + 20.0");

        #100 $finish;
    end
endmodule

sim_output/fpadd_tb.vcd
$date
	Tue Sep 23 01:32:04 2025
$end
$version
	Icarus Verilog
$end
$timescale
	1ps
$end
$scope module fpadd_tb $end
$var wire 32 ! sum_s [31:0] $end
$var wire 64 " sum_d [63:0] $end
$var wire 3 # fex_s [2:0] $end
$var wire 3 $ fex_d [2:0] $end
$var wire 1 % done_s $end
$var wire 1 & done_d $end
$var reg 64 ' a_d [63:0] $end
$var reg 32 ( a_s [31:0] $end
$var reg 64 ) b_d [63:0] $end
$var reg 32 * b_s [31:0] $end
$var reg 1 + clk $end
$var reg 1 , rst $end
$var reg 1 - valid $end
$scope module dut_double $end
$var wire 64 . a [63:0] $end
$var wire 64 / b [63:0] $end
$var wire 1 + clk $end
$var wire 11 0 expa_wire_s0 [10:0] $end
$var wire 11 1 expb_wire_s0 [10:0] $end
$var wire 1 2 isinf_a $end
$var wire 1 3 isinf_b $end
$var wire 1 4 isnan_a $end
$var wire 1 5 isnan_b $end
$var wire 1 6 issubnorm_a $end
$var wire 1 7 issubnorm_b $end
$var wire 1 8 iszero_a $end
$var wire 1 9 iszero_b $end
$var wire 52 : mana_wire_s0 [51:0] $end
$var wire 52 ; manb_wire_s0 [51:0] $end
$var wire 1 , rst $end
$var wire 1 < sign_a_wire_s0 $end
$var wire 1 = sign_b_wire_s0 $end
$var wire 1 - valid $end
$var reg 1 & done $end
$var reg 11 > exp_normalized_s3 [10:0] $end
$var reg 11 ? exp_result_s2 [10:0] $end
$var reg 11 @ expa_s0 [10:0] $end
$var reg 11 A expb_s0 [10:0] $end
$var reg 12 B expdiff_s1 [11:0] $end
$var reg 3 C fex [2:0] $end
$var reg 52 D final_mantissa [51:0] $end
$var reg 1 E guard_bit $end
$var reg 64 F input_a_s0 [63:0] $end
$var reg 64 G input_b_s0 [63:0] $end
$var reg 58 H man_normalized_s3 [57:0] $end
$var reg 58 I man_result_s2 [57:0] $end
$var reg 55 J mana_full [54:0] $end
$var reg 57 K mana_imm_s1 [56:0] $end
$var reg 52 L mana_s0 [51:0] $end
$var reg 55 M manb_full [54:0] $end
$var reg 57 N manb_imm_s1 [56:0] $end
$var reg 52 O manb_s0 [51:0] $end
$var reg 11 P max_exp_s1 [10:0] $end
$var reg 1 Q round_bit $end
$var reg 1 R round_up $end
$var reg 1 S sign_a $end
$var reg 1 T sign_a_s1 $end
$var reg 1 U sign_b $end
$var reg 1 V sign_b_s1 $end
$var reg 1 W sign_result_s2 $end
$var reg 1 X sign_result_s3 $end
$var reg 1 Y special_case_s0 $end
$var reg 1 Z special_case_s1 $end
$var reg 1 [ special_case_s2 $end
$var reg 1 \ special_case_s3 $end
$var reg 3 ] special_fex_s0 [2:0] $end
$var reg 3 ^ special_fex_s1 [2:0] $end
$var reg 3 _ special_fex_s2 [2:0] $end
$var reg 3 ` special_fex_s3 [2:0] $end
$var reg 64 a special_result_s0 [63:0] $end
$var reg 64 b special_result_s1 [63:0] $end
$var reg 64 c special_result_s2 [63:0] $end
$var reg 64 d special_result_s3 [63:0] $end
$var reg 1 e sticky_bit $end
$var reg 64 f sum [63:0] $end
$var reg 1 g valid_s1 $end
$var reg 1 h valid_s2 $end
$var reg 1 i valid_s3 $end
$var reg 1 j valid_s4 $end
$scope function count_leading_zeros $end
$var reg 1 k found $end
$var reg 58 l mantissa [57:0] $end
$var integer 32 m j [31:0] $end
$upscope $end
$upscope $end
$scope module dut_single $end
$var wire 32 n a [31:0] $end
$var wire 32 o b [31:0] $end
$var wire 1 + clk $end
$var wire 8 p expa_wire_s0 [7:0] $end
$var wire 8 q expb_wire_s0 [7:0] $end
$var wire 1 r isinf_a $end
$var wire 1 s isinf_b $end
$var wire 1 t isnan_a $end
$var wire 1 u isnan_b $end
$var wire 1 v issubnorm_a $end
$var wire 1 w issubnorm_b $end
$var wire 1 x iszero_a $end
$var wire 1 y iszero_b $end
$var wire 23 z mana_wire_s0 [22:0] $end
$var wire 23 { manb_wire_s0 [22:0] $end
$var wire 1 , rst $end
$var wire 1 | sign_a_wire_s0 $end
$var wire 1 } sign_b_wire_s0 $end
$var wire 1 - valid $end
$var reg 1 % done $end
$var reg 8 ~ exp_normalized_s3 [7:0] $end
$var reg 8 !" exp_result_s2 [7:0] $end
$var reg 8 "" expa_s0 [7:0] $end
$var reg 8 #" expb_s0 [7:0] $end
$var reg 9 $" expdiff_s1 [8:0] $end
$var reg 3 %" fex [2:0] $end
$var reg 23 &" final_mantissa [22:0] $end
$var reg 1 '" guard_bit $end
$var reg 32 (" input_a_s0 [31:0] $end
$var reg 32 )" input_b_s0 [31:0] $end
$var reg 29 *" man_normalized_s3 [28:0] $end
$var reg 29 +" man_result_s2 [28:0] $end
$var reg 26 ," mana_full [25:0] $end
$var reg 28 -" mana_imm_s1 [27:0] $end
$var reg 23 ." mana_s0 [22:0] $end
$var reg 26 /" manb_full [25:0] $end
$var reg 28 0" manb_imm_s1 [27:0] $end
$var reg 23 1" manb_s0 [22:0] $end
$var reg 8 2" max_exp_s1 [7:0] $end
$var reg 1 3" round_bit $end
$var reg 1 4" round_up $end
$var reg 1 5" sign_a $end
$var reg 1 6" sign_a_s1 $end
$var reg 1 7" sign_b $end
$var reg 1 8" sign_b_s1 $end
$var reg 1 9" sign_result_s2 $end
$var reg 1 :" sign_result_s3 $end
$var reg 1 ;" special_case_s0 $end
$var reg 1 <" special_case_s1 $end
$var reg 1 =" special_case_s2 $end
$var reg 1 >" special_case_s3 $end
$var reg 3 ?" special_fex_s0 [2:0] $end
$var reg 3 @" special_fex_s1 [2:0] $end
$var reg 3 A" special_fex_s2 [2:0] $end
$var reg 3 B" special_fex_s3 [2:0] $end
$var reg 32 C" special_result_s0 [31:0] $end
$var reg 32 D" special_result_s1 [31:0] $end
$var reg 32 E" special_result_s2 [31:0] $end
$var reg 32 F" special_result_s3 [31:0] $end
$var reg 1 G" sticky_bit $end
$var reg 32 H" sum [31:0] $end
$var reg 1 I" valid_s1 $end
$var reg 1 J" valid_s2 $end
$var reg 1 K" valid_s3 $end
$var reg 1 L" valid_s4 $end
$scope function count_leading_zeros $end
$var reg 1 M" found $end
$var reg 29 N" mantissa [28:0] $end
$var integer 32 O" j [31:0] $end
$upscope $end
$upscope $end
$scope task print_result $end
$var reg 1024 P" name [1023:0] $end
$upscope $end
$upscope $end
$enddefinitions $end
#0
$dumpvars
bx P"
bx O"
bx N"
xM"
0L"
0K"
0J"
0I"
b0 H"
xG"
b0 F"
b0 E"
b0 D"
b0 C"
b0 B"
b0 A"
b0 @"
b0 ?"
0>"
0="
0<"
0;"
0:"
09"
08"
07"
06"
05"
x4"
x3"
b0 2"
b0 1"
b0 0"
bx /"
b0 ."
b0 -"
bx ,"
b0 +"
b0 *"
b0 )"
b0 ("
x'"
bx &"
b0 %"
b0 $"
b0 #"
b0 ""
b0 !"
b0 ~
0}
0|
b0 {
b0 z
1y
1x
0w
0v
0u
0t
0s
0r
b0 q
b0 p
b0 o
b0 n
bx m
bx l
xk
0j
0i
0h
0g
b0 f
xe
b0 d
b0 c
b0 b
b0 a
b0 `
b0 _
b0 ^
b0 ]
0\
0[
0Z
0Y
0X
0W
0V
0U
0T
0S
xR
xQ
b0 P
b0 O
b0 N
bx M
b0 L
b0 K
bx J
b0 I
b0 H
b0 G
b0 F
xE
bx D
b0 C
b0 B
b0 A
b0 @
b0 ?
b0 >
0=
0<
b0 ;
b0 :
19
18
07
06
05
04
03
02
b0 1
b0 0
b0 /
b0 .
0-
1,
0+
b0 *
b0 )
b0 (
b0 '
0&
0%
b0 $
b0 #
b0 "
b0 !
$end
#5000
1+
#10000
0+
#15000
1+
#20000
0+
b100000000111001000000000000000000000000000000000000000000000000 )
b100000000111001000000000000000000000000000000000000000000000000 /
b1000001011000000000000000000000 *
b1000001011000000000000000000000 o
b100000000110100000000000000000000000000000000000000000000000000 '
b100000000110100000000000000000000000000000000000000000000000000 .
b1000001001000000000000000000000 (
b1000001001000000000000000000000 n
1-
0,
#25000
09
08
0y
0x
bx00 K
bx00 N
1Y
b1000000000000000000000000000000000000000000000000000000 M
b1000000000000000000000000000000000000000000000000000000 J
b100000000111001000000000000000000000000000000000000000000000000 G
b100000000110100000000000000000000000000000000000000000000000000 F
b1001000000000000000000000000000000000000000000000000 ;
b1001000000000000000000000000000000000000000000000000 O
b100000000000000000000000000000000000000000000000000 :
b100000000000000000000000000000000000000000000000000 L
b10000000011 1
b10000000011 A
b10000000011 0
b10000000011 @
1g
bx00 -"
bx00 0"
1;"
b10000000000000000000000000 /"
b10000000000000000000000000 ,"
b1000001011000000000000000000000 )"
b1000001001000000000000000000000 ("
b11000000000000000000000 {
b11000000000000000000000 1"
b1000000000000000000000 z
b1000000000000000000000 ."
b10000010 q
b10000010 #"
b10000010 p
b10000010 ""
1I"
1+
#30000
0+
#35000
1J"
0;"
b11100000000000000000000000 /"
b10100000000000000000000000 ,"
b10000010 2"
b1000000000000000000000000000 -"
b1000000000000000000000000000 0"
1<"
bx +"
1h
0Y
b1100100000000000000000000000000000000000000000000000000 M
b1010000000000000000000000000000000000000000000000000000 J
b10000000011 P
b100000000000000000000000000000000000000000000000000000000 K
b100000000000000000000000000000000000000000000000000000000 N
1Z
bx I
1+
#40000
0+
0-
#45000
bx H
b1000000000000000000000000000000000000000000000000000000000 I
b10000000011 ?
1[
b101000000000000000000000000000000000000000000000000000000 K
b110010000000000000000000000000000000000000000000000000000 N
0Z
1i
0g
bx *"
b10000000000000000000000000000 +"
b10000010 !"
1="
b1010000000000000000000000000 -"
b1110000000000000000000000000 0"
0<"
1K"
0I"
1+
#50000
0+
#55000
1L"
0J"
b11000000000000000000000000000 +"
0="
b10000011 ~
b1000000000000000000000000000 *"
1>"
1j
0h
b1011010000000000000000000000000000000000000000000000000000 I
0[
b10000000100 >
b100000000000000000000000000000000000000000000000000000000 H
1\
1+
#60000
0+
#65000
1&
b101101000000000000000000000000000000000000000000000000000 H
0\
0i
1%
b1100000000000000000000000000 *"
0>"
0K"
1+
#70000
0+
#75000
0L"
b1000001110000000000000000000000 !
b1000001110000000000000000000000 H"
0j
b100000001000110100000000000000000000000000000000000000000000000 "
b100000001000110100000000000000000000000000000000000000000000000 f
b10000000000000000000000 &"
04"
0'"
0G"
03"
b110100000000000000000000000000000000000000000000000 D
0R
0E
0e
0Q
1+
#80000
0+
#85000
0&
0%
1+
#90000
0+
b100000001001110000000000000000000000000000000000000000000000000 )
b100000001001110000000000000000000000000000000000000000000000000 /
b1000010101000000000000000000000 *
b1000010101000000000000000000000 o
b100000001000100000000000000000000000000000000000000000000000000 '
b100000001000100000000000000000000000000000000000000000000000000 .
b1000010001000000000000000000000 (
b1000010001000000000000000000000 n
1-
b11000100110000001011100011000000100000001010110010000000110001001101000010111000110000 P"
#95000
1I"
b1000000000000000000000 {
b1000000000000000000000 1"
b10000101 q
b10000101 #"
b10000100 p
b10000100 ""
b1000010101000000000000000000000 )"
b1000010001000000000000000000000 ("
1g
b1110000000000000000000000000000000000000000000000000 ;
b1110000000000000000000000000000000000000000000000000 O
b10000000100 1
b10000000100 A
b10000000100 0
b10000000100 @
b100000001001110000000000000000000000000000000000000000000000000 G
b100000001000100000000000000000000000000000000000000000000000000 F
1+
#100000
0+
#105000
b10000000100 P
b1111000000000000000000000000000000000000000000000000000 M
1h
b10000100 2"
b111111111 $"
b10100000000000000000000000 /"
1J"
1+
#110000
0+
0-
#115000
1K"
0I"
b10000101 2"
b1010000000000000000000000000 0"
b101000000000000000000000000 -"
b10000100 !"
1i
0g
b111100000000000000000000000000000000000000000000000000000 N
b10000000100 ?
1+
#120000
0+
#125000
b10000000101 >
b1100100000000000000000000000000000000000000000000000000000 I
1j
0h
b10000101 ~
b1111000000000000000000000000 +"
b10000101 !"
1L"
0J"
1+
#130000
0+
#135000
0K"
b1111000000000000000000000000 *"
b1000010110000000000000000000000 !
b1000010110000000000000000000000 H"
1%
0i
b110010000000000000000000000000000000000000000000000000000 H
b100000001010110100000000000000000000000000000000000000000000000 "
b100000001010110100000000000000000000000000000000000000000000000 f
1&
1+
#140000
0+
#145000
b100000001011001000000000000000000000000000000000000000000000000 "
b100000001011001000000000000000000000000000000000000000000000000 f
0j
b1000010111100000000000000000000 !
b1000010111100000000000000000000 H"
0L"
b1001000000000000000000000000000000000000000000000000 D
b11100000000000000000000 &"
1+
#150000
0+
#155000
0%
0&
1+
#160000
0+
b100000000000000000000000000000000000000000000000000000000000000 )
b100000000000000000000000000000000000000000000000000000000000000 /
b1000000000000000000000000000000 *
b1000000000000000000000000000000 o
b11111111110000000000000000000000000000000000000000000000000000 '
b11111111110000000000000000000000000000000000000000000000000000 .
b111111100000000000000000000000 (
b111111100000000000000000000000 n
1-
b11010000110000001011100011000000100000001010110010000000111000001100000010111000110000 P"
#165000
b100000000000000000000000000000000000000000000000000000000000000 G
b11111111110000000000000000000000000000000000000000000000000000 F
b0 ;
b0 O
b0 :
b0 L
b10000000000 1
b10000000000 A
b1111111111 0
b1111111111 @
1g
b1000000000000000000000000000000 )"
b111111100000000000000000000000 ("
b0 {
b0 1"
b0 z
b0 ."
b10000000 q
b10000000 #"
b1111111 p
b1111111 ""
1I"
1+
#170000
0+
#175000
1J"
b10000000000000000000000000 /"
b10000000000000000000000000 ,"
b10000000 2"
1h
b1000000000000000000000000000000000000000000000000000000 M
b1000000000000000000000000000000000000000000000000000000 J
b1111111111 P
b111111111111 B
1+
#180000
0+
0-
#185000
b1111111111 ?
b10000000000 P
b100000000000000000000000000000000000000000000000000000000 N
b10000000000000000000000000000000000000000000000000000000 K
1i
0g
b10000000 !"
b1000000000000000000000000000 0"
b100000000000000000000000000 -"
1K"
0I"
1+
#190000
0+
#195000
1L"
0J"
b1100000000000000000000000000 +"
b10000000 ~
1j
0h
b110000000000000000000000000000000000000000000000000000000 I
b10000000000 ?
b10000000000 >
1+
#200000
0+
#205000
b100000000001001000000000000000000000000000000000000000000000000 "
b100000000001001000000000000000000000000000000000000000000000000 f
1&
b110000000000000000000000000000000000000000000000000000000 H
0i
b1000000011100000000000000000000 !
b1000000011100000000000000000000 H"
1%
b1100000000000000000000000000 *"
0K"
1+
#210000
0+
#215000
0L"
b1000000010000000000000000000000 !
b1000000010000000000000000000000 H"
0j
b100000000001000000000000000000000000000000000000000000000000000 "
b100000000001000000000000000000000000000000000000000000000000000 f
b10000000000000000000000 &"
b1000000000000000000000000000000000000000000000000000 D
1+
#220000
0+
#225000
0&
0%
1+
#230000
0+
b100000001100010000000000000000000000000000000000000000000000000 )
b100000001100010000000000000000000000000000000000000000000000000 /
b1000010111100000000000000000000 *
b1000010111100000000000000000000 o
b100000001010101000000000000000000000000000000000000000000000000 '
b100000001010101000000000000000000000000000000000000000000000000 .
b1000010011100000000000000000000 (
b1000010011100000000000000000000 n
1-
b1100010010111000110000001000000010101100100000001100100010111000110000 P"
