rtl/fpmul.v
module fpmul #(
    parameter DWIDTH = 32,
    parameter EWIDTH = 8,
    parameter MWIDTH = 23
)(
    input  clk,
    input  rst,
    input  valid,
    input  [DWIDTH-1:0] a,
    input  [DWIDTH-1:0] b,
    output reg [DWIDTH-1:0] result,
    output reg [2:0] fex,  // [overflow, underflow, inexact]
    output reg done
);

    localparam BIAS = (1 << (EWIDTH-1)) - 1;
    localparam MAX_EXP = (1 << EWIDTH) - 1;
    
    // Stage 0: Unpack and classify
    reg signed [EWIDTH:0] expa_s0, expb_s0;
    reg [MWIDTH-1:0] mana_s0, manb_s0;
    reg sign_a_s0, sign_b_s0;
    reg valid_s0, valid_s1, valid_s2;

    always @(posedge clk or posedge rst) begin
        if (rst) begin
            expa_s0 <= 0; expb_s0 <= 0;
            mana_s0 <= 0; manb_s0 <= 0;
            sign_a_s0 <= 0; sign_b_s0 <= 0;
            valid_s0 <= 0;
        end else if (valid) begin
            expa_s0 <= {1'b0, a[DWIDTH-2 : MWIDTH]};
            expb_s0 <= {1'b0, b[DWIDTH-2 : MWIDTH]};
            mana_s0 <= a[MWIDTH-1:0];
            manb_s0 <= b[MWIDTH-1:0];
            sign_a_s0 <= a[DWIDTH-1];
            sign_b_s0 <= b[DWIDTH-1];
            valid_s0 <= 1;
        end else begin
            valid_s0 <= valid;
        end
    end

    wire isnan_a     = (expa_s0[EWIDTH-1:0] == MAX_EXP) && (mana_s0 != 0);
    wire isnan_b     = (expb_s0[EWIDTH-1:0] == MAX_EXP) && (manb_s0 != 0);
    wire isinf_a     = (expa_s0[EWIDTH-1:0] == MAX_EXP) && (mana_s0 == 0);
    wire isinf_b     = (expb_s0[EWIDTH-1:0] == MAX_EXP) && (manb_s0 == 0);
    wire issubnorm_a = (expa_s0[EWIDTH-1:0] == 0) && (mana_s0 != 0);
    wire issubnorm_b = (expb_s0[EWIDTH-1:0] == 0) && (manb_s0 != 0);
    wire iszero_a    = (expa_s0[EWIDTH-1:0] == 0) && (mana_s0 == 0);
    wire iszero_b    = (expb_s0[EWIDTH-1:0] == 0) && (manb_s0 == 0);

    wire [MWIDTH:0] mana_full = issubnorm_a ? {1'b0, mana_s0} : {1'b1, mana_s0};
    wire [MWIDTH:0] manb_full = issubnorm_b ? {1'b0, manb_s0} : {1'b1, manb_s0};

    function [5:0] count_leading_zeros;
        input [MWIDTH:0] mantissa;
        integer i;
        reg found;
        begin
            found = 0;
            count_leading_zeros = MWIDTH;
            for (i = MWIDTH; i >= 0; i = i - 1) begin
                if (mantissa[i] == 1'b1 && !found) begin
                    count_leading_zeros = MWIDTH - i;
                    found = 1;
                end
            end
        end
    endfunction

    function [5:0] priority_encode_product;
        input [2*(MWIDTH+1)-1:0] product;
        integer i;
        reg found;
        begin
            priority_encode_product = 1;
            found = 0;
            for (i = 2*(MWIDTH+1)-2; i >= 2*(MWIDTH+1)-2-MWIDTH; i = i - 1) begin
                if ((product[i] == 1'b1) && !found) begin
                    priority_encode_product = (2*(MWIDTH+1)-2) - i;
                    found = 1;
                end else if ((i == 2*(MWIDTH+1)-2-MWIDTH) && !found) begin
                    priority_encode_product = MWIDTH + 1;
                    found = 1;
                end
            end
        end
    endfunction

    wire [5:0] lz_count_a = issubnorm_a ? count_leading_zeros(mana_full) : 0;
    wire [5:0] lz_count_b = issubnorm_b ? count_leading_zeros(manb_full) : 0;

    wire [MWIDTH:0] mana_norm = issubnorm_a ? (mana_full << lz_count_a) : mana_full;
    wire [MWIDTH:0] manb_norm = issubnorm_b ? (manb_full << lz_count_b) : manb_full;

    wire special_case = isnan_a || isnan_b || isinf_a || isinf_b || iszero_a || iszero_b;
    
    reg [DWIDTH-1:0] special_result;
    reg [2:0] special_fex;
    reg special_case_s0, special_case_s1, special_case_s2;

    always @(*) begin
        special_result = 0;
        special_fex = 3'b000;
        
        if (isnan_a || isnan_b) begin
            special_result = {1'b0, {EWIDTH{1'b1}}, 1'b1, {(MWIDTH-1){1'b0}}};
            special_fex = 3'b000;
        end
        else if ((iszero_a && isinf_b) || (isinf_a && iszero_b)) begin
            special_result = {1'b0, {EWIDTH{1'b1}}, 1'b1, {(MWIDTH-1){1'b0}}};
            special_fex = 3'b000;
        end
        else if (isinf_a || isinf_b) begin
            special_result = {sign_a_s0 ^ sign_b_s0, {EWIDTH{1'b1}}, {MWIDTH{1'b0}}};
            special_fex = 3'b000;
        end
        else if (iszero_a || iszero_b) begin
            special_result = {sign_a_s0 ^ sign_b_s0, {(EWIDTH+MWIDTH){1'b0}}};
            special_fex = 3'b000;
        end
    end

    // Stage 1: Multiply
    reg sign_result_s1;
    reg signed [EWIDTH+1:0] exp_result_s1;
    reg [2*(MWIDTH+1)-1:0] man_product_s1;

    always @(posedge clk or posedge rst) begin
        if (rst) begin
            valid_s1 <= 0;
            special_case_s1 <= 0;
            sign_result_s1 <= 0;
            exp_result_s1 <= 0;
            man_product_s1 <= 0;
        end else begin
            valid_s1 <= valid_s0;
            special_case_s1 <= special_case;
            
            if (valid_s0) begin
                sign_result_s1 <= sign_a_s0 ^ sign_b_s0;
                man_product_s1 <= mana_norm * manb_norm;
                
                if (special_case) begin
                    exp_result_s1 <= 0;
                end else begin
                    if (issubnorm_a && issubnorm_b) begin
                        exp_result_s1 <= 0;
                    end else if (issubnorm_a) begin
                        exp_result_s1 <= expb_s0 + 1 - BIAS - lz_count_a;
                    end else if (issubnorm_b) begin
                        exp_result_s1 <= expa_s0 + 1 - BIAS - lz_count_b;
                    end else begin
                        exp_result_s1 <= expa_s0 + expb_s0 - BIAS;
                    end
                end
            end
        end
    end
    // Stage 2: Normalize and round
    reg sign_result_s2;
    reg [EWIDTH-1:0] exp_final_s2;
    reg [MWIDTH-1:0] man_final_s2;
    reg [2:0] fex_s2;

    wire [5:0] lz_count_product;
    wire [2*(MWIDTH+1)-1:0] normalized_product;
    wire signed [EWIDTH+1:0] normalized_exp;
    wire [MWIDTH:0] mantissa_rounded;
    wire [MWIDTH:0] subnormal_mantissa;
    wire guard_bit, round_bit, sticky_bit;
    wire should_round_up;

    assign lz_count_product = priority_encode_product(man_product_s1);

    wire product_overflow = man_product_s1[2*(MWIDTH+1)-1];
    wire product_underflow = !man_product_s1[2*(MWIDTH+1)-1] && !man_product_s1[2*(MWIDTH+1)-2] && (man_product_s1 != 0);

    // Calculate normalized product and exponent
    assign normalized_product = product_overflow ? (man_product_s1 >> 1) :
                            product_underflow ? (man_product_s1 << (lz_count_product > exp_result_s1 ? exp_result_s1[5:0] : lz_count_product)) :
                            man_product_s1;

    assign normalized_exp = product_overflow ? (exp_result_s1 + 1) :
                        product_underflow ? (exp_result_s1 - (lz_count_product > exp_result_s1 ? exp_result_s1[5:0] : lz_count_product)) :
                        exp_result_s1;

    assign mantissa_rounded = normalized_product[2*(MWIDTH+1)-2 : 2*(MWIDTH+1)-2-MWIDTH];
    assign guard_bit = normalized_product[2*(MWIDTH+1)-2-MWIDTH-1];
    assign round_bit = normalized_product[2*(MWIDTH+1)-2-MWIDTH-2];
    assign sticky_bit = |normalized_product[2*(MWIDTH+1)-2-MWIDTH-3:0];

    // Round to Zero (truncate)
    assign should_round_up = 0;

    wire is_subnormal = (normalized_exp <= 0);
    wire [5:0] subnormal_shift = is_subnormal ? (1 - normalized_exp) : 0;
    assign subnormal_mantissa = mantissa_rounded >> subnormal_shift;

    always @(posedge clk or posedge rst) begin
        if (rst) begin
            valid_s2 <= 0;
            special_case_s2 <= 0;
            sign_result_s2 <= 0;
            exp_final_s2 <= 0;
            man_final_s2 <= 0;
            fex_s2 <= 0;
        end else begin
            valid_s2 <= valid_s1;
            special_case_s2 <= special_case_s1;
            
            if (valid_s1) begin
                if (special_case_s1) begin
                    // Handle special cases
                    sign_result_s2 <= special_result[DWIDTH-1];
                    exp_final_s2 <= special_result[DWIDTH-2:MWIDTH];
                    man_final_s2 <= special_result[MWIDTH-1:0];
                    fex_s2 <= special_fex;
                end else begin
                    sign_result_s2 <= sign_result_s1;
                    fex_s2 <= 3'b000; 
                    
                    // Check for overflow
                    if (normalized_exp >= MAX_EXP) begin
                        exp_final_s2 <= {EWIDTH{1'b1}};  
                        man_final_s2 <= {MWIDTH{1'b0}}; 
                        fex_s2 <= 3'b100; 
                    end
                    // Check for underflow to zero
                    else if (normalized_exp < -(MWIDTH)) begin
                        exp_final_s2 <= {EWIDTH{1'b0}};
                        man_final_s2 <= {MWIDTH{1'b0}};
                        fex_s2 <= 3'b010;  
                    end
                    // Subnormal result
                    else if (is_subnormal) begin
                        exp_final_s2 <= {EWIDTH{1'b0}};
                        if (should_round_up && (subnormal_mantissa != {(MWIDTH+1){1'b1}})) begin
                            man_final_s2 <= subnormal_mantissa[MWIDTH-1:0] + 1;
                        end else begin
                            man_final_s2 <= subnormal_mantissa[MWIDTH-1:0];
                        end
                        fex_s2[1] <= 1'b1; 
                        if (guard_bit || round_bit || sticky_bit) begin
                            fex_s2[0] <= 1'b1; 
                        end
                    end
                    // Normal result
                    else begin
                        if (should_round_up) begin
                            if (mantissa_rounded == {(MWIDTH+1){1'b1}}) begin
                                if ((normalized_exp + 1) >= MAX_EXP) begin
                                    exp_final_s2 <= {EWIDTH{1'b1}};
                                    man_final_s2 <= {MWIDTH{1'b0}};
                                    fex_s2 <= 3'b100;
                                end else begin
                                    exp_final_s2 <= normalized_exp[EWIDTH-1:0] + 1;
                                    man_final_s2 <= {MWIDTH{1'b0}};
                                    fex_s2 <= 3'b001;  // inexact
                                end
                            end else begin
                                exp_final_s2 <= normalized_exp[EWIDTH-1:0];
                                man_final_s2 <= mantissa_rounded[MWIDTH-1:0] + 1;
                                fex_s2 <= 3'b1;  // inexact
                            end
                        end else begin
                            exp_final_s2 <= normalized_exp[EWIDTH-1:0];
                            man_final_s2 <= mantissa_rounded[MWIDTH-1:0];
                            if (guard_bit || round_bit || sticky_bit) begin
                                fex_s2 <= 3'b1;  // inexact
                            end
                        end
                    end
                end
            end
        end
    end

    // Output
    always @(posedge clk or posedge rst) begin
        if (rst) begin
            result <= 0;
            fex <= 0;
            done <= 0;
        end else begin
            done <= valid_s2;
            if (valid_s2) begin
                result <= {sign_result_s2, exp_final_s2, man_final_s2};
                fex <= fex_s2;
            end
        end
    end

endmodule

tb/fpmul_tb.v
`timescale 1ns / 1ps

module fpmul_tb;
    // Parameters
    parameter DWIDTH = 32;
    parameter EWIDTH = 8;
    parameter MWIDTH = 23;
    parameter CLK_PERIOD = 10;

    // Testbench signals
    reg clk;
    reg rst;
    reg valid;
    reg [DWIDTH-1:0] a, b;
    wire [DWIDTH-1:0] sum;
    wire [2:0] fex;
    wire done;

    integer i;

    // DUT instantiation
    fpmul #(
        .DWIDTH(DWIDTH),
        .EWIDTH(EWIDTH),
        .MWIDTH(MWIDTH)
    ) dut (
        .clk(clk),
        .rst(rst),
        .valid(valid),
        .a(a),
        .b(b),
        .result(sum),
        .fex(fex),
        .done(done)
    );

    // Clock
    always #(CLK_PERIOD/2) clk = ~clk;

    // Some normal inputs (decimal → IEEE-754 hex)
    reg [31:0] test_a [0:9];
    reg [31:0] test_b [0:9];
    reg [31:0] expected [0:9];

    initial begin
        $dumpfile("fpmul.vcd");
        $dumpvars(0, fpmul_tb);
        // Example normal numbers
        test_a[0] = 32'h3F800000; test_b[0] = 32'h40000000; expected[0] = 32'h40000000; // 1 * 2 = 2
        test_a[1] = 32'h40490FDB; test_b[1] = 32'h3F800000; expected[1] = 32'h40490FDB; // pi * 1 = pi
        test_a[2] = 32'h40000000; test_b[2] = 32'h40400000; expected[2] = 32'h40C00000; // 2 * 3 = 6
        test_a[3] = 32'h41200000; test_b[3] = 32'h3F800000; expected[3] = 32'h41200000; // 10 * 1 = 10
        test_a[4] = 32'h3F000000; test_b[4] = 32'h3F800000; expected[4] = 32'h3F000000; // 0.5 * 1 = 0.5
        test_a[5] = 32'h3EAAAAAB; test_b[5] = 32'h3F800000; expected[5] = 32'h3EAAAAAB; // 0.3333 * 1 = 0.3333
        test_a[6] = 32'h40400000; test_b[6] = 32'h40400000; expected[6] = 32'h41100000; // 3 * 3 = 9
        test_a[7] = 32'h40A00000; test_b[7] = 32'h3F800000; expected[7] = 32'h40A00000; // 5 * 1 = 5
        test_a[8] = 32'h3FCCCCCD; test_b[8] = 32'h3F4CCCCD; expected[8] = 32'h3fa3d70a; // 1.6 * 0.8 ≈ 1.28
        test_a[9] = 32'h40700000; test_b[9] = 32'h3F800000; expected[9] = 32'h40700000; // 3.75 * 1 = 3.75
    end

    // Simulation
    initial begin
        clk = 0; rst = 1; valid = 0; a = 0; b = 0;
        #(CLK_PERIOD*3);
        rst = 0;

        for (i=0; i<10; i=i+1) begin
            a = test_a[i];
            b = test_b[i];
            valid = 1;
            @(posedge clk);
            valid = 0;

            // Wait for pipeline (3 cycles)
            repeat(3) @(posedge clk);

            $display("Test %0d: a=0x%08h, b=0x%08h -> product=0x%08h, expected=0x%08h, fex=%b", 
                      i, a, b, sum, expected[i], fex);

            if (sum !== expected[i])
                $display("  --> FAIL");
            else
                $display("  --> PASS");
        end

        $display("=== Testbench finished ===");
        $finish;
    end
endmodule

sim_output/fpmul.vcd
$date
	Tue Sep 23 01:12:25 2025
$end
$version
	Icarus Verilog
$end
$timescale
	1ps
$end
$scope module fpmul_tb $end
$var wire 32 ! sum [31:0] $end
$var wire 3 " fex [2:0] $end
$var wire 1 # done $end
$var reg 32 $ a [31:0] $end
$var reg 32 % b [31:0] $end
$var reg 1 & clk $end
$var reg 1 ' rst $end
$var reg 1 ( valid $end
$var integer 32 ) i [31:0] $end
$scope module dut $end
$var wire 32 * a [31:0] $end
$var wire 32 + b [31:0] $end
$var wire 1 & clk $end
$var wire 1 , isinf_a $end
$var wire 1 - isinf_b $end
$var wire 1 . isnan_a $end
$var wire 1 / isnan_b $end
$var wire 1 0 issubnorm_a $end
$var wire 1 1 issubnorm_b $end
$var wire 1 2 iszero_a $end
$var wire 1 3 iszero_b $end
$var wire 1 4 product_underflow $end
$var wire 1 ' rst $end
$var wire 1 5 should_round_up $end
$var wire 1 6 special_case $end
$var wire 1 ( valid $end
$var wire 6 7 subnormal_shift [5:0] $end
$var wire 24 8 subnormal_mantissa [23:0] $end
$var wire 1 9 sticky_bit $end
$var wire 1 : round_bit $end
$var wire 1 ; product_overflow $end
$var wire 48 < normalized_product [47:0] $end
$var wire 10 = normalized_exp [9:0] $end
$var wire 24 > mantissa_rounded [23:0] $end
$var wire 24 ? manb_norm [23:0] $end
$var wire 24 @ manb_full [23:0] $end
$var wire 24 A mana_norm [23:0] $end
$var wire 24 B mana_full [23:0] $end
$var wire 6 C lz_count_product [5:0] $end
$var wire 6 D lz_count_b [5:0] $end
$var wire 6 E lz_count_a [5:0] $end
$var wire 1 F is_subnormal $end
$var wire 1 G guard_bit $end
$var reg 1 # done $end
$var reg 8 H exp_final_s2 [7:0] $end
$var reg 10 I exp_result_s1 [9:0] $end
$var reg 9 J expa_s0 [8:0] $end
$var reg 9 K expb_s0 [8:0] $end
$var reg 3 L fex [2:0] $end
$var reg 3 M fex_s2 [2:0] $end
$var reg 23 N man_final_s2 [22:0] $end
$var reg 48 O man_product_s1 [47:0] $end
$var reg 23 P mana_s0 [22:0] $end
$var reg 23 Q manb_s0 [22:0] $end
$var reg 32 R result [31:0] $end
$var reg 1 S sign_a_s0 $end
$var reg 1 T sign_b_s0 $end
$var reg 1 U sign_result_s1 $end
$var reg 1 V sign_result_s2 $end
$var reg 1 W special_case_s1 $end
$var reg 1 X special_case_s2 $end
$var reg 3 Y special_fex [2:0] $end
$var reg 32 Z special_result [31:0] $end
$var reg 1 [ valid_s0 $end
$var reg 1 \ valid_s1 $end
$var reg 1 ] valid_s2 $end
$scope function count_leading_zeros $end
$var reg 1 ^ found $end
$var reg 24 _ mantissa [23:0] $end
$var integer 32 ` i [31:0] $end
$upscope $end
$scope function priority_encode_product $end
$var reg 1 a found $end
$var reg 48 b product [47:0] $end
$var integer 32 c i [31:0] $end
$upscope $end
$upscope $end
$upscope $end
$enddefinitions $end
#0
$dumpvars
b10110 c
b0 b
1a
b11111111111111111111111111111111 `
b100000000000000000000000 _
1^
0]
0\
0[
b0 Z
b0 Y
0X
0W
0V
0U
0T
0S
b0 R
b0 Q
b0 P
b0 O
b0 N
b0 M
b0 L
b0 K
b0 J
b0 I
b0 H
0G
1F
b0 E
b0 D
b11000 C
b100000000000000000000000 B
b100000000000000000000000 A
b100000000000000000000000 @
b100000000000000000000000 ?
b0 >
b0 =
b0 <
0;
0:
09
b0 8
b1 7
16
05
04
13
12
01
00
0/
0.
0-
0,
b0 +
b0 *
bx )
0(
1'
0&
b0 %
b0 $
0#
b0 "
b0 !
$end
#5000
1&
#10000
0&
#15000
1&
#20000
0&
#25000
1&
#30000
0&
1(
b1000000000000000000000000000000 %
b1000000000000000000000000000000 +
b111111100000000000000000000000 $
b111111100000000000000000000000 *
b0 )
0'
#35000
1W
0(
1&
#40000
0&
#45000
1X
1&
#50000
0&
#55000
1&
#60000
0&
#65000
06
b11111111111111111111111111111111 `
1^
b110010010000111111011011 _
b110010010000111111011011 A
03
02
b110010010000111111011011 B
1[
b10010010000111111011011 P
b1111111 K
b10000000 J
1(
b111111100000000000000000000000 %
b111111100000000000000000000000 +
b1000000010010010000111111011011 $
b1000000010010010000111111011011 *
b1 )
1&
#70000
0&
#75000
b0 7
b110010010000111111011011 8
b110010010000111111011011 >
0F
b10000000 =
b11001001000011111101101100000000000000000000000 <
b0 C
b10110 c
1a
b11001001000011111101101100000000000000000000000 b
04
0[
b10000000 I
b11001001000011111101101100000000000000000000000 O
0W
1\
0(
1&
#80000
0&
#85000
b10010010000111111011011 N
b10000000 H
0X
1]
0\
1&
#90000
0&
#95000
0]
b1000000010010010000111111011011 !
b1000000010010010000111111011011 R
1#
1&
#100000
0&
#105000
b110000000000000000000000 ?
b11111111111111111111111111111111 `
1^
b110000000000000000000000 _
b100000000000000000000000 A
b110000000000000000000000 @
b100000000000000000000000 B
0#
1[
b10000000000000000000000 Q
b0 P
b10000000 K
1(
b1000000010000000000000000000000 %
b1000000010000000000000000000000 +
b1000000000000000000000000000000 $
b1000000000000000000000000000000 *
b10 )
1&
#110000
0&
#115000
b110000000000000000000000 8
b110000000000000000000000 >
b10000001 =
b11000000000000000000000000000000000000000000000 <
b10110 c
1a
b11000000000000000000000000000000000000000000000 b
0[
b10000001 I
b11000000000000000000000000000000000000000000000 O
1\
0(
1&
#120000
0&
#125000
b10000000000000000000000 N
b10000001 H
1]
0\
1&
#130000
0&
#135000
0]
b1000000110000000000000000000000 !
b1000000110000000000000000000000 R
1#
1&
#140000
0&
#145000
b100000000000000000000000 ?
b11111111111111111111111111111111 `
1^
b100000000000000000000000 _
b101000000000000000000000 A
b100000000000000000000000 @
b101000000000000000000000 B
0#
1[
b0 Q
b1000000000000000000000 P
b1111111 K
b10000010 J
1(
b111111100000000000000000000000 %
b111111100000000000000000000000 +
b1000001001000000000000000000000 $
b1000001001000000000000000000000 *
b11 )
1&
#150000
0&
#155000
b101000000000000000000000 8
b101000000000000000000000 >
b10000010 =
b10100000000000000000000000000000000000000000000 <
b10110 c
1a
b10100000000000000000000000000000000000000000000 b
0[
b10000010 I
b10100000000000000000000000000000000000000000000 O
1\
0(
1&
#160000
0&
#165000
b1000000000000000000000 N
b10000010 H
1]
0\
1&
#170000
0&
#175000
0]
b1000001001000000000000000000000 !
b1000001001000000000000000000000 R
1#
1&
#180000
0&
#185000
b11111111111111111111111111111111 `
1^
b100000000000000000000000 A
b100000000000000000000000 B
0#
1[
b0 P
b1111110 J
1(
b111111000000000000000000000000 $
b111111000000000000000000000000 *
b100 )
1&
#190000
0&
#195000
b100000000000000000000000 8
b100000000000000000000000 >
b1111110 =
b10000000000000000000000000000000000000000000000 <
b10110 c
1a
b10000000000000000000000000000000000000000000000 b
0[
b1111110 I
b10000000000000000000000000000000000000000000000 O
1\
0(
1&
#200000
0&
#205000
b0 N
b1111110 H
1]
0\
1&
#210000
0&
#215000
0]
b111111000000000000000000000000 !
b111111000000000000000000000000 R
1#
1&
#220000
0&
#225000
b11111111111111111111111111111111 `
1^
b101010101010101010101011 _
b101010101010101010101011 A
b101010101010101010101011 B
0#
1[
b1010101010101010101011 P
b1111101 J
1(
b111110101010101010101010101011 $
b111110101010101010101010101011 *
b101 )
1&
#230000
0&
#235000
b101010101010101010101011 8
b101010101010101010101011 >
b1111101 =
b10101010101010101010101100000000000000000000000 <
b10110 c
1a
b10101010101010101010101100000000000000000000000 b
0[
b1111101 I
b10101010101010101010101100000000000000000000000 O
1\
0(
1&
#240000
0&
#245000
b1010101010101010101011 N
b1111101 H
1]
0\
1&
#250000
0&
#255000
0]
b111110101010101010101010101011 !
b111110101010101010101010101011 R
1#
1&
#260000
0&
#265000
b110000000000000000000000 ?
b11111111111111111111111111111111 `
1^
b110000000000000000000000 _
b110000000000000000000000 A
b110000000000000000000000 @
b110000000000000000000000 B
0#
1[
b10000000000000000000000 Q
b10000000000000000000000 P
b10000000 K
b10000000 J
1(
b1000000010000000000000000000000 %
b1000000010000000000000000000000 +
b1000000010000000000000000000000 $
b1000000010000000000000000000000 *
b110 )
1&
#270000
0&
#275000
b100100000000000000000000 8
b100100000000000000000000 >
b10000010 =
b10010000000000000000000000000000000000000000000 <
b10 C
b10110 c
1a
b100100000000000000000000000000000000000000000000 b
1;
0[
b10000001 I
b100100000000000000000000000000000000000000000000 O
1\
0(
1&
#280000
0&
#285000
b100000000000000000000 N
b10000010 H
1]
0\
1&
#290000
0&
#295000
0]
b1000001000100000000000000000000 !
b1000001000100000000000000000000 R
1#
1&
#300000
0&
#305000
b100000000000000000000000 ?
b11111111111111111111111111111111 `
1^
b100000000000000000000000 _
b101000000000000000000000 A
b100000000000000000000000 @
b101000000000000000000000 B
0#
1[
b0 Q
b1000000000000000000000 P
b1111111 K
b10000001 J
1(
b111111100000000000000000000000 %
b111111100000000000000000000000 +
b1000000101000000000000000000000 $
b1000000101000000000000000000000 *
b111 )
1&
#310000
0&
#315000
b101000000000000000000000 8
b101000000000000000000000 >
b10000001 =
b10100000000000000000000000000000000000000000000 <
b0 C
b10110 c
1a
b10100000000000000000000000000000000000000000000 b
0;
0[
b10100000000000000000000000000000000000000000000 O
1\
0(
1&
#320000
0&
#325000
b1000000000000000000000 N
b10000001 H
1]
0\
1&
#330000
0&
#335000
0]
b1000000101000000000000000000000 !
b1000000101000000000000000000000 R
1#
1&
#340000
0&
#345000
b110011001100110011001101 ?
b11111111111111111111111111111111 `
1^
b110011001100110011001101 _
b110011001100110011001101 A
b110011001100110011001101 @
b110011001100110011001101 B
0#
1[
b10011001100110011001101 Q
b10011001100110011001101 P
b1111110 K
b1111111 J
1(
b111111010011001100110011001101 %
b111111010011001100110011001101 +
b111111110011001100110011001101 $
b111111110011001100110011001101 *
b1000 )
1&
#350000
0&
#355000
b101000111101011100001010 8
b101000111101011100001010 >
1G
19
b1111111 =
b10100011110101110000101010001111010111000010100 <
b1 C
b10110 c
1a
b101000111101011100001010100011110101110000101001 b
1;
0[
b1111110 I
b101000111101011100001010100011110101110000101001 O
1\
0(
1&
#360000
0&
#365000
b1 M
b1000111101011100001010 N
b1111111 H
1]
0\
1&
#370000
0&
#375000
0]
b1 "
b1 L
b111111101000111101011100001010 !
b111111101000111101011100001010 R
1#
1&
#380000
0&
#385000
b100000000000000000000000 ?
b11111111111111111111111111111111 `
1^
b100000000000000000000000 _
b111100000000000000000000 A
b100000000000000000000000 @
b111100000000000000000000 B
0#
1[
b0 Q
b11100000000000000000000 P
b1111111 K
b10000000 J
1(
b111111100000000000000000000000 %
b111111100000000000000000000000 +
b1000000011100000000000000000000 $
b1000000011100000000000000000000 *
b1001 )
1&
#390000
0&
#395000
b111100000000000000000000 8
b111100000000000000000000 >
0G
09
b11110000000000000000000000000000000000000000000 <
b10000000 =
b0 C
b10110 c
1a
b11110000000000000000000000000000000000000000000 b
0;
0[
b10000000 I
b11110000000000000000000000000000000000000000000 O
1\
0(
1&
#400000
0&
#405000
b11100000000000000000000 N
b10000000 H
b0 M
1]
0\
1&
#410000
0&
#415000
0]
b0 "
b0 L
b1000000011100000000000000000000 !
b1000000011100000000000000000000 R
1#
1&
#420000
0&
#425000
0#
b1010 )
1&
